trueapi/__init__.py
trueapi_cli-0.0.1.dist-info/LICENSE
trueapi_cli-0.0.1.dist-info/METADATA
trueapi_cli-0.0.1.dist-info/WHEEL
trueapi_cli-0.0.1.dist-info/top_level.txt
trueapi_cli-0.0.1.dist-info/RECORD
